safeguardcredentialtype/__init__.py
safeguardcredentialtype-1.1.195978.dist-info/LICENSE
safeguardcredentialtype-1.1.195978.dist-info/METADATA
safeguardcredentialtype-1.1.195978.dist-info/WHEEL
safeguardcredentialtype-1.1.195978.dist-info/entry_points.txt
safeguardcredentialtype-1.1.195978.dist-info/top_level.txt
safeguardcredentialtype-1.1.195978.dist-info/RECORD
