Metadata-Version: 2.1
Name: safeguardcredentialtype
Version: 1.1.195978
Summary: One Identity Safeguard Credential Type plugin for Ansible
Home-page: http://oneidentity.com
Author: One Identity, Llc.
Author-email: brad.nicholes@oneidentity.com
License: Apache 2.0
Keywords: ansible,One Identity
License-File: LICENSE
Requires-Dist: pysafeguard
